{"php_version":"8.5.3","php_ast_extension_version":"1.1.4dev","ast_version_used":120,"supported_versions":[50,60,70,80,85,90,100,110,120],"tokens":[[394,"<?php\n",1],[397,"\n",2],[392,"\/\/ Coverage:",3],[397,"\n",3],[392,"\/\/ - LIT-CONST-001",4],[397,"\n",4],[392,"\/\/ - CAST-STRING-001",5],[397,"\n",5],[392,"\/\/ - FUNC-DECL-004",6],[397,"\n",6],[392,"\/\/ - TYPE-PARAM-001",7],[397,"\n",7],[392,"\/\/ - VAR-CHAIN-002",8],[397,"\n\n",8],[310,"function",10],[397," ",10],[262,"describe",10],"(",[262,"int",10],[397," ",10],[266,"$count",10],",",[397," ",10],[262,"float",10],[397," ",10],[266,"$ratio",10],",",[397," ",10],[262,"bool",10],[397," ",10],[266,"$flag",10],",",[397," ",10],[262,"string",10],[397," ",10],[266,"$label",10],")",":",[397," ",10],[262,"string",10],[397," ",10],"{",[397,"\n\t",10],[266,"$text",11],[397," ",11],"=",[397," ",11],[383,"(string)",11],[266,"$count",11],";",[397,"\n\t",11],[266,"$copy",12],[397," ",12],"=",[397," ",12],[266,"$label",12],";",[397,"\n\t",12],[313,"return",13],[397," ",13],[266,"$copy",13],";",[397,"\n",13],"}",[397,"\n\n",14],[310,"function",16],[397," ",16],[262,"read_limit",16],"(",")",":",[397," ",16],[262,"int",16],[397," ",16],"{",[397,"\n\t",16],[266,"$limit",17],[397," ",17],"=",[397," ",17],[262,"PHP_INT_MAX",17],";",[397,"\n\t",17],[313,"return",18],[397," ",18],[266,"$limit",18],";",[397,"\n",18],"}",[397,"\n\n",19],[310,"function",21],[397," ",21],[262,"combine",21],"(",[262,"int",21],[397," ",21],[266,"$left",21],",",[397," ",21],[262,"int",21],[397," ",21],[266,"$right",21],",",[397," ",21],[262,"bool",21],[397," ",21],[266,"$flag",21],")",":",[397," ",21],[262,"int",21],[397," ",21],"{",[397,"\n\t",21],[266,"$total",22],[397," ",22],"=",[397," ",22],[266,"$left",22],[397," ",22],"+",[397," ",22],[266,"$right",22],";",[397,"\n\t",22],[266,"$copy",23],[397," ",23],"=",[397," ",23],[266,"$total",23],";",[397,"\n\t",23],[313,"return",24],[397," ",24],[266,"$copy",24],";",[397,"\n",24],"}",[397,"\n\n",25],[266,"$a",27],[397," ",27],"=",[397," ",27],[262,"read_limit",27],"(",")",";",[397,"\n",27],[266,"$b",28],[397," ",28],"=",[397," ",28],[261,"2.5",28],";",[397,"\n",28],[266,"$c",29],[397," ",29],"=",[397," ",29],[262,"true",29],";",[397,"\n",29],[266,"$d",30],[397," ",30],"=",[397," ",30],[269,"\"limit\"",30],";",[397,"\n",30],[266,"$e",31],[397," ",31],"=",[397," ",31],[262,"describe",31],"(",[266,"$a",31],",",[397," ",31],[266,"$b",31],",",[397," ",31],[266,"$c",31],",",[397," ",31],[266,"$d",31],")",";",[397,"\n",31],[266,"$f",32],[397," ",32],"=",[397," ",32],[266,"$e",32],";",[397,"\n",32],[266,"$g",33],[397," ",33],"=",[397," ",33],[262,"combine",33],"(",[260,"1",33],",",[397," ",33],[260,"2",33],",",[397," ",33],[266,"$c",33],")",";",[397,"\n",33],[266,"$h",34],[397," ",34],"=",[397," ",34],[262,"combine",34],"(",[266,"$g",34],",",[397," ",34],[260,"3",34],",",[397," ",34],[266,"$c",34],")",";",[397,"\n",34]],"ast":{"kind":132,"flags":0,"lineno":1,"children":[{"kind":68,"flags":0,"lineno":10,"children":{"name":"describe","docComment":null,"params":{"kind":136,"flags":0,"lineno":10,"children":[{"kind":1536,"flags":0,"lineno":10,"children":{"type":{"kind":1,"flags":4,"lineno":10,"children":[]},"name":"count","default":null,"attributes":null,"docComment":null,"hooks":null}},{"kind":1536,"flags":0,"lineno":10,"children":{"type":{"kind":1,"flags":5,"lineno":10,"children":[]},"name":"ratio","default":null,"attributes":null,"docComment":null,"hooks":null}},{"kind":1536,"flags":0,"lineno":10,"children":{"type":{"kind":1,"flags":18,"lineno":10,"children":[]},"name":"flag","default":null,"attributes":null,"docComment":null,"hooks":null}},{"kind":1536,"flags":0,"lineno":10,"children":{"type":{"kind":1,"flags":6,"lineno":10,"children":[]},"name":"label","default":null,"attributes":null,"docComment":null,"hooks":null}}]},"stmts":{"kind":132,"flags":0,"lineno":10,"children":[{"kind":518,"flags":0,"lineno":11,"children":{"var":{"kind":256,"flags":0,"lineno":11,"children":{"name":"text"}},"expr":{"kind":261,"flags":6,"lineno":11,"children":{"expr":{"kind":256,"flags":0,"lineno":11,"children":{"name":"count"}}}}}},{"kind":518,"flags":0,"lineno":12,"children":{"var":{"kind":256,"flags":0,"lineno":12,"children":{"name":"copy"}},"expr":{"kind":256,"flags":0,"lineno":12,"children":{"name":"label"}}}},{"kind":278,"flags":0,"lineno":13,"children":{"expr":{"kind":256,"flags":0,"lineno":13,"children":{"name":"copy"}}}}]},"returnType":{"kind":1,"flags":6,"lineno":10,"children":[]},"attributes":null,"__declId":0},"endLineno":14},{"kind":68,"flags":0,"lineno":16,"children":{"name":"read_limit","docComment":null,"params":{"kind":136,"flags":0,"lineno":16,"children":[]},"stmts":{"kind":132,"flags":0,"lineno":16,"children":[{"kind":518,"flags":0,"lineno":17,"children":{"var":{"kind":256,"flags":0,"lineno":17,"children":{"name":"limit"}},"expr":{"kind":257,"flags":0,"lineno":17,"children":{"name":{"kind":2048,"flags":1,"lineno":17,"children":{"name":"PHP_INT_MAX"}}}}}},{"kind":278,"flags":0,"lineno":18,"children":{"expr":{"kind":256,"flags":0,"lineno":18,"children":{"name":"limit"}}}}]},"returnType":{"kind":1,"flags":4,"lineno":16,"children":[]},"attributes":null,"__declId":1},"endLineno":19},{"kind":68,"flags":0,"lineno":21,"children":{"name":"combine","docComment":null,"params":{"kind":136,"flags":0,"lineno":21,"children":[{"kind":1536,"flags":0,"lineno":21,"children":{"type":{"kind":1,"flags":4,"lineno":21,"children":[]},"name":"left","default":null,"attributes":null,"docComment":null,"hooks":null}},{"kind":1536,"flags":0,"lineno":21,"children":{"type":{"kind":1,"flags":4,"lineno":21,"children":[]},"name":"right","default":null,"attributes":null,"docComment":null,"hooks":null}},{"kind":1536,"flags":0,"lineno":21,"children":{"type":{"kind":1,"flags":18,"lineno":21,"children":[]},"name":"flag","default":null,"attributes":null,"docComment":null,"hooks":null}}]},"stmts":{"kind":132,"flags":0,"lineno":21,"children":[{"kind":518,"flags":0,"lineno":22,"children":{"var":{"kind":256,"flags":0,"lineno":22,"children":{"name":"total"}},"expr":{"kind":521,"flags":1,"lineno":22,"children":{"left":{"kind":256,"flags":0,"lineno":22,"children":{"name":"left"}},"right":{"kind":256,"flags":0,"lineno":22,"children":{"name":"right"}}}}}},{"kind":518,"flags":0,"lineno":23,"children":{"var":{"kind":256,"flags":0,"lineno":23,"children":{"name":"copy"}},"expr":{"kind":256,"flags":0,"lineno":23,"children":{"name":"total"}}}},{"kind":278,"flags":0,"lineno":24,"children":{"expr":{"kind":256,"flags":0,"lineno":24,"children":{"name":"copy"}}}}]},"returnType":{"kind":1,"flags":4,"lineno":21,"children":[]},"attributes":null,"__declId":2},"endLineno":25},{"kind":518,"flags":0,"lineno":27,"children":{"var":{"kind":256,"flags":0,"lineno":27,"children":{"name":"a"}},"expr":{"kind":516,"flags":0,"lineno":27,"children":{"expr":{"kind":2048,"flags":1,"lineno":27,"children":{"name":"read_limit"}},"args":{"kind":128,"flags":0,"lineno":27,"children":[]}}}}},{"kind":518,"flags":0,"lineno":28,"children":{"var":{"kind":256,"flags":0,"lineno":28,"children":{"name":"b"}},"expr":2.5}},{"kind":518,"flags":0,"lineno":29,"children":{"var":{"kind":256,"flags":0,"lineno":29,"children":{"name":"c"}},"expr":{"kind":257,"flags":0,"lineno":29,"children":{"name":{"kind":2048,"flags":1,"lineno":29,"children":{"name":"true"}}}}}},{"kind":518,"flags":0,"lineno":30,"children":{"var":{"kind":256,"flags":0,"lineno":30,"children":{"name":"d"}},"expr":"limit"}},{"kind":518,"flags":0,"lineno":31,"children":{"var":{"kind":256,"flags":0,"lineno":31,"children":{"name":"e"}},"expr":{"kind":516,"flags":0,"lineno":31,"children":{"expr":{"kind":2048,"flags":1,"lineno":31,"children":{"name":"describe"}},"args":{"kind":128,"flags":0,"lineno":31,"children":[{"kind":256,"flags":0,"lineno":31,"children":{"name":"a"}},{"kind":256,"flags":0,"lineno":31,"children":{"name":"b"}},{"kind":256,"flags":0,"lineno":31,"children":{"name":"c"}},{"kind":256,"flags":0,"lineno":31,"children":{"name":"d"}}]}}}}},{"kind":518,"flags":0,"lineno":32,"children":{"var":{"kind":256,"flags":0,"lineno":32,"children":{"name":"f"}},"expr":{"kind":256,"flags":0,"lineno":32,"children":{"name":"e"}}}},{"kind":518,"flags":0,"lineno":33,"children":{"var":{"kind":256,"flags":0,"lineno":33,"children":{"name":"g"}},"expr":{"kind":516,"flags":0,"lineno":33,"children":{"expr":{"kind":2048,"flags":1,"lineno":33,"children":{"name":"combine"}},"args":{"kind":128,"flags":0,"lineno":33,"children":[1,2,{"kind":256,"flags":0,"lineno":33,"children":{"name":"c"}}]}}}}},{"kind":518,"flags":0,"lineno":34,"children":{"var":{"kind":256,"flags":0,"lineno":34,"children":{"name":"h"}},"expr":{"kind":516,"flags":0,"lineno":34,"children":{"expr":{"kind":2048,"flags":1,"lineno":34,"children":{"name":"combine"}},"args":{"kind":128,"flags":0,"lineno":34,"children":[{"kind":256,"flags":0,"lineno":34,"children":{"name":"g"}},3,{"kind":256,"flags":0,"lineno":34,"children":{"name":"c"}}]}}}}}]}}