{"php_version":"8.5.3","php_ast_extension_version":"1.1.4dev","ast_version_used":120,"supported_versions":[50,60,70,80,85,90,100,110,120],"tokens":[[394,"<?php\n",1],[397,"\n",2],[392,"\/\/ Coverage:",3],[397,"\n",3],[392,"\/\/ - CLASS-STATIC-NS-001",4],[397,"\n",4],[392,"\/\/ - CLASS-STATIC-NS-003",5],[397,"\n",5],[392,"\/\/ - CLASS-NS-002",6],[397,"\n",6],[392,"\/\/ - CLASS-NS-003",7],[397,"\n\n",7],[342,"namespace",9],[397," ",9],[265,"StageTwo\\StaticMatrix",9],";",[397,"\n\n",9],[336,"class",11],[397," ",11],[262,"LocalFactory",11],[397," ",11],"{",[397,"\n\t",11],[326,"public",12],[397," ",12],[321,"static",12],[397," ",12],[310,"function",12],[397," ",12],[262,"make",12],"(",")",":",[397," ",12],[262,"int",12],[397," ",12],"{",[397,"\n\t\t",12],[313,"return",13],[397," ",13],[260,"41",13],";",[397,"\n\t",13],"}",[397,"\n",14],"}",[397,"\n\n",15],[336,"class",17],[397," ",17],[262,"OtherFactory",17],[397," ",17],"{",[397,"\n\t",17],[326,"public",18],[397," ",18],[321,"static",18],[397," ",18],[310,"function",18],[397," ",18],[262,"make",18],"(",")",":",[397," ",18],[262,"int",18],[397," ",18],"{",[397,"\n\t\t",18],[313,"return",19],[397," ",19],[260,"1",19],";",[397,"\n\t",19],"}",[397,"\n",20],"}",[397,"\n\n",21],[310,"function",23],[397," ",23],[262,"local_instance_call",23],"(",")",":",[397," ",23],[262,"int",23],[397," ",23],"{",[397,"\n\t",23],[266,"$local",24],[397," ",24],"=",[397," ",24],[284,"new",24],[397," ",24],[262,"LocalFactory",24],"(",")",";",[397,"\n\t",24],[266,"$value",25],[397," ",25],"=",[397," ",25],[266,"$local",25],[402,"::",25],[262,"make",25],"(",")",";",[397,"\n\t",25],[313,"return",26],[397," ",26],[266,"$value",26],";",[397,"\n",26],"}",[397,"\n\n",27],[310,"function",29],[397," ",29],[262,"rooted_instance_call",29],"(",")",":",[397," ",29],[262,"int",29],[397," ",29],"{",[397,"\n\t",29],[266,"$other",30],[397," ",30],"=",[397," ",30],[284,"new",30],[397," ",30],[263,"\\StageTwo\\StaticMatrix\\OtherFactory",30],"(",")",";",[397,"\n\t",30],[266,"$value",31],[397," ",31],"=",[397," ",31],[266,"$other",31],[402,"::",31],[262,"make",31],"(",")",";",[397,"\n\t",31],[313,"return",32],[397," ",32],[266,"$value",32],";",[397,"\n",32],"}",[397,"\n\n",33],[266,"$a",35],[397," ",35],"=",[397," ",35],[262,"local_instance_call",35],"(",")",";",[397,"\n",35],[266,"$b",36],[397," ",36],"=",[397," ",36],[262,"rooted_instance_call",36],"(",")",";",[397,"\n",36],[266,"$c",37],[397," ",37],"=",[397," ",37],[266,"$a",37],[397," ",37],"+",[397," ",37],[266,"$b",37],";",[397,"\n",37]],"ast":{"kind":132,"flags":0,"lineno":1,"children":[{"kind":542,"flags":0,"lineno":9,"children":{"name":"StageTwo\\StaticMatrix","stmts":null}},{"kind":71,"flags":0,"lineno":11,"children":{"name":"LocalFactory","docComment":null,"extends":null,"implements":null,"stmts":{"kind":132,"flags":0,"lineno":11,"children":[{"kind":70,"flags":17,"lineno":12,"children":{"name":"make","docComment":null,"params":{"kind":136,"flags":0,"lineno":12,"children":[]},"stmts":{"kind":132,"flags":0,"lineno":12,"children":[{"kind":278,"flags":0,"lineno":13,"children":{"expr":41}}]},"returnType":{"kind":1,"flags":4,"lineno":12,"children":[]},"attributes":null,"__declId":0},"endLineno":14}]},"attributes":null,"type":null,"__declId":1},"endLineno":15},{"kind":71,"flags":0,"lineno":17,"children":{"name":"OtherFactory","docComment":null,"extends":null,"implements":null,"stmts":{"kind":132,"flags":0,"lineno":17,"children":[{"kind":70,"flags":17,"lineno":18,"children":{"name":"make","docComment":null,"params":{"kind":136,"flags":0,"lineno":18,"children":[]},"stmts":{"kind":132,"flags":0,"lineno":18,"children":[{"kind":278,"flags":0,"lineno":19,"children":{"expr":1}}]},"returnType":{"kind":1,"flags":4,"lineno":18,"children":[]},"attributes":null,"__declId":2},"endLineno":20}]},"attributes":null,"type":null,"__declId":3},"endLineno":21},{"kind":68,"flags":0,"lineno":23,"children":{"name":"local_instance_call","docComment":null,"params":{"kind":136,"flags":0,"lineno":23,"children":[]},"stmts":{"kind":132,"flags":0,"lineno":23,"children":[{"kind":518,"flags":0,"lineno":24,"children":{"var":{"kind":256,"flags":0,"lineno":24,"children":{"name":"local"}},"expr":{"kind":527,"flags":0,"lineno":24,"children":{"class":{"kind":2048,"flags":1,"lineno":24,"children":{"name":"LocalFactory"}},"args":{"kind":128,"flags":0,"lineno":24,"children":[]}}}}},{"kind":518,"flags":0,"lineno":25,"children":{"var":{"kind":256,"flags":0,"lineno":25,"children":{"name":"value"}},"expr":{"kind":770,"flags":0,"lineno":25,"children":{"class":{"kind":256,"flags":0,"lineno":25,"children":{"name":"local"}},"method":"make","args":{"kind":128,"flags":0,"lineno":25,"children":[]}}}}},{"kind":278,"flags":0,"lineno":26,"children":{"expr":{"kind":256,"flags":0,"lineno":26,"children":{"name":"value"}}}}]},"returnType":{"kind":1,"flags":4,"lineno":23,"children":[]},"attributes":null,"__declId":4},"endLineno":27},{"kind":68,"flags":0,"lineno":29,"children":{"name":"rooted_instance_call","docComment":null,"params":{"kind":136,"flags":0,"lineno":29,"children":[]},"stmts":{"kind":132,"flags":0,"lineno":29,"children":[{"kind":518,"flags":0,"lineno":30,"children":{"var":{"kind":256,"flags":0,"lineno":30,"children":{"name":"other"}},"expr":{"kind":527,"flags":0,"lineno":30,"children":{"class":{"kind":2048,"flags":0,"lineno":30,"children":{"name":"StageTwo\\StaticMatrix\\OtherFactory"}},"args":{"kind":128,"flags":0,"lineno":30,"children":[]}}}}},{"kind":518,"flags":0,"lineno":31,"children":{"var":{"kind":256,"flags":0,"lineno":31,"children":{"name":"value"}},"expr":{"kind":770,"flags":0,"lineno":31,"children":{"class":{"kind":256,"flags":0,"lineno":31,"children":{"name":"other"}},"method":"make","args":{"kind":128,"flags":0,"lineno":31,"children":[]}}}}},{"kind":278,"flags":0,"lineno":32,"children":{"expr":{"kind":256,"flags":0,"lineno":32,"children":{"name":"value"}}}}]},"returnType":{"kind":1,"flags":4,"lineno":29,"children":[]},"attributes":null,"__declId":5},"endLineno":33},{"kind":518,"flags":0,"lineno":35,"children":{"var":{"kind":256,"flags":0,"lineno":35,"children":{"name":"a"}},"expr":{"kind":516,"flags":0,"lineno":35,"children":{"expr":{"kind":2048,"flags":1,"lineno":35,"children":{"name":"local_instance_call"}},"args":{"kind":128,"flags":0,"lineno":35,"children":[]}}}}},{"kind":518,"flags":0,"lineno":36,"children":{"var":{"kind":256,"flags":0,"lineno":36,"children":{"name":"b"}},"expr":{"kind":516,"flags":0,"lineno":36,"children":{"expr":{"kind":2048,"flags":1,"lineno":36,"children":{"name":"rooted_instance_call"}},"args":{"kind":128,"flags":0,"lineno":36,"children":[]}}}}},{"kind":518,"flags":0,"lineno":37,"children":{"var":{"kind":256,"flags":0,"lineno":37,"children":{"name":"c"}},"expr":{"kind":521,"flags":1,"lineno":37,"children":{"left":{"kind":256,"flags":0,"lineno":37,"children":{"name":"a"}},"right":{"kind":256,"flags":0,"lineno":37,"children":{"name":"b"}}}}}}]}}