{"php_version":"8.5.3","php_ast_extension_version":"1.1.4dev","ast_version_used":120,"supported_versions":[50,60,70,80,85,90,100,110,120],"tokens":[[394,"<?php\n",1],[299,"declare",2],"(",[262,"strict_types",2],"=",[260,"1",2],")",";",[397,"\n\n",2],[393,"\/** @var array<int,int> *\/",4],[397,"\n",4],[266,"$v",5],[397," ",5],"=",[397," ",5],"[",[260,"1",5],",",[260,"2",5],",",[260,"3",5],"]",";",[397,"\n\n",5],[297,"foreach",7],[397," ",7],"(",[266,"$v",7],[397," ",7],[301,"as",7],[397," ",7],[266,"$value",7],")",[397," ",7],"{",[397,"\n    ",7],[266,"$value",8],[397," ",8],"=",[397," ",8],[260,"10",8],";",[397," ",8],[392,"\/\/ should NOT affect array",8],[397,"\n",8],"}",[397,"\n\n",9],[297,"foreach",11],[397," ",11],"(",[266,"$v",11],[397," ",11],[301,"as",11],[397," ",11],[266,"$k",11],[397," ",11],[391,"=>",11],[397," ",11],[266,"$value",11],")",[397," ",11],"{",[397,"\n    ",11],[291,"echo",12],[397," ",12],[266,"$k",12],",",[397," ",12],[269,"\":\"",12],",",[397," ",12],[266,"$value",12],",",[397," ",12],[269,"\"\\n\"",12],";",[397,"\n",12],"}",[397,"\n",13]],"ast":{"kind":132,"flags":0,"lineno":1,"children":[{"kind":538,"flags":0,"lineno":2,"children":{"declares":{"kind":139,"flags":0,"lineno":2,"children":[{"kind":775,"flags":0,"lineno":2,"children":{"name":"strict_types","value":1,"docComment":null}}]},"stmts":null}},{"kind":518,"flags":0,"lineno":5,"children":{"var":{"kind":256,"flags":0,"lineno":5,"children":{"name":"v"}},"expr":{"kind":129,"flags":3,"lineno":5,"children":[{"kind":526,"flags":0,"lineno":5,"children":{"value":1,"key":null}},{"kind":526,"flags":0,"lineno":5,"children":{"value":2,"key":null}},{"kind":526,"flags":0,"lineno":5,"children":{"value":3,"key":null}}]}}},{"kind":1025,"flags":0,"lineno":7,"children":{"expr":{"kind":256,"flags":0,"lineno":7,"children":{"name":"v"}},"value":{"kind":256,"flags":0,"lineno":7,"children":{"name":"value"}},"key":null,"stmts":{"kind":132,"flags":0,"lineno":7,"children":[{"kind":518,"flags":0,"lineno":8,"children":{"var":{"kind":256,"flags":0,"lineno":8,"children":{"name":"value"}},"expr":10}}]}}},{"kind":1025,"flags":0,"lineno":11,"children":{"expr":{"kind":256,"flags":0,"lineno":11,"children":{"name":"v"}},"value":{"kind":256,"flags":0,"lineno":11,"children":{"name":"value"}},"key":{"kind":256,"flags":0,"lineno":11,"children":{"name":"k"}},"stmts":{"kind":132,"flags":0,"lineno":11,"children":[{"kind":282,"flags":0,"lineno":12,"children":{"expr":{"kind":256,"flags":0,"lineno":12,"children":{"name":"k"}}}},{"kind":282,"flags":0,"lineno":12,"children":{"expr":":"}},{"kind":282,"flags":0,"lineno":12,"children":{"expr":{"kind":256,"flags":0,"lineno":12,"children":{"name":"value"}}}},{"kind":282,"flags":0,"lineno":12,"children":{"expr":"\n"}}]}}}]}}